yahp/__init__.py
yahp/auto_hparams.py
yahp/field.py
yahp/hparams.py
yahp/inheritance.py
yahp/py.typed
yahp/serialization.py
yahp/types.py
yahp/version.py
yahp/create_object/__init__.py
yahp/create_object/argparse.py
yahp/create_object/commented_map.py
yahp/create_object/create_object.py
yahp/utils/__init__.py
yahp/utils/interactive.py
yahp/utils/iter_helpers.py
yahp/utils/json_schema_helpers.py
yahp/utils/type_helpers.py
yahp/utils/typing_future.py
yahp-0.1.3.dist-info/LICENSE
yahp-0.1.3.dist-info/LICENSE_HEADER
yahp-0.1.3.dist-info/METADATA
yahp-0.1.3.dist-info/WHEEL
yahp-0.1.3.dist-info/top_level.txt
yahp-0.1.3.dist-info/RECORD
